uInterface-1.0.2.dist-info/METADATA
uInterface-1.0.2.dist-info/WHEEL
uInterface-1.0.2.dist-info/license_files/LICENSE
u_interface.libs/libssl-dc1f8b35.so.3
u_interface.libs/libcrypto-8fa3e0f7.so.3
LICENSE
gui/docs.md
u_interface/__init__.py
u_interface/u_interface.cpython-310-x86_64-linux-gnu.so
uInterface-1.0.2.dist-info/RECORD
