Metadata-Version: 2.1
Name: uInterface
Version: 1.0.2
Classifier: Programming Language :: Rust
Classifier: Programming Language :: Python :: Implementation :: CPython
Classifier: Programming Language :: Python :: Implementation :: PyPy
License-File: LICENSE
Summary: Crate to allow easy requests to uHunt's API
License: Apache-2.0
Requires-Python: >=3.7
Project-URL: Source Code, https://github.com/LovetheFrogs/uInterface
